{
    "year": "2022",
    "events": [
        {
            "date": "6月18日",
            "prefecture": "大阪",
            "course": "枚方国際ゴルフ倶楽部",
            "tel": "072-858-8311"
        },
        {
            "date": "6月12日",
            "prefecture": "兵庫",
            "course": "随縁カントリークラブ 西神戸コース",
            "tel": "078-997-9700"
        },
        {
            "date": "6月7日",
            "prefecture": "大阪",
            "course": "枚方国際ゴルフ倶楽部",
            "tel": "072-858-8311"
        },
        {
            "date": "5月31日",
            "prefecture": "大阪",
            "course": "枚方国際ゴルフ倶楽部",
            "tel": "072-858-8311"
        },
        {
            "date": "5月31日",
            "prefecture": "兵庫",
            "course": "猪名川国際カントリークラブ",
            "tel": "072-766-0500"
        },
        {
            "date": "5月23日",
            "prefecture": "兵庫",
            "course": "チェリーゴルフときわ台コース",
            "tel": "072-738-2035"
        },
        {
            "date": "5月22日",
            "prefecture": "大阪",
            "course": "枚方国際ゴルフ倶楽部",
            "tel": "072-858-8311"
        },
        {
            "date": "5月18日",
            "prefecture": "兵庫",
            "course": "三木セブンハンドレッド倶楽部",
            "tel": "0794-87-3131"
        },
        {
            "date": "5月11日",
            "prefecture": "大阪",
            "course": "枚方国際ゴルフ倶楽部",
            "tel": "072-858-8311"
        },
        {
            "date": "5月8日",
            "prefecture": "兵庫",
            "course": "随縁カントリークラブ 西神戸コース",
            "tel": "078-997-9700"
        },
        {
            "date": "5月3日",
            "prefecture": "三重",
            "course": "亀山ゴルフクラブ",
            "tel": "0595-82-6511"
        },
        {
            "date": "5月2日",
            "prefecture": "大阪",
            "course": "枚方国際ゴルフ倶楽部",
            "tel": "072-858-8311"
        },
        {
            "date": "4月27日",
            "prefecture": "大阪",
            "course": "枚方国際ゴルフ倶楽部",
            "tel": "072-858-8311"
        },
        {
            "date": "4月25日",
            "prefecture": "兵庫",
            "course": "チェリーゴルフときわ台コース",
            "tel": "072-738-2035"
        },
        {
            "date": "4月17日",
            "prefecture": "兵庫",
            "course": "猪名川国際カントリークラブ",
            "tel": "072-766-0500"
        },
        {
            "date": "4月16日",
            "prefecture": "大阪",
            "course": "枚方国際ゴルフ倶楽部",
            "tel": "072-858-8311"
        },
        {
            "date": "4月11日",
            "prefecture": "兵庫",
            "course": "チェリーゴルフときわ台コース",
            "tel": "072-738-2035"
        },
        {
            "date": "4月10日",
            "prefecture": "兵庫",
            "course": "随縁カントリークラブ 西神戸コース",
            "tel": "078-997-9700"
        },
        {
            "date": "4月5日",
            "prefecture": "大阪",
            "course": "枚方国際ゴルフ倶楽部",
            "tel": "072-858-8311"
        },
        {
            "date": "3月30日",
            "prefecture": "兵庫",
            "course": "猪名川国際カントリークラブ",
            "tel": "072-766-0500"
        },
        {
            "date": "3月29日",
            "prefecture": "兵庫",
            "course": "チェリーゴルフときわ台コース",
            "tel": "072-738-2035"
        },
        {
            "date": "3月28日",
            "prefecture": "大阪",
            "course": "枚方国際ゴルフ倶楽部",
            "tel": "072-858-8311"
        },
        {
            "date": "3月13日",
            "prefecture": "兵庫",
            "course": "随縁カントリークラブ 西神戸コース",
            "tel": "078-997-9700"
        },
        {
            "date": "3月9日",
            "prefecture": "兵庫",
            "course": "三木セブンハンドレッド倶楽部",
            "tel": "0794-87-3131"
        },
        {
            "date": "3月6日",
            "prefecture": "大阪",
            "course": "枚方国際ゴルフ倶楽部",
            "tel": "072-858-8311"
        },
        {
            "date": "3月6日",
            "prefecture": "兵庫",
            "course": "チェリーゴルフときわ台コース",
            "tel": "072-738-2035"
        },
        {
            "date": "2月28日",
            "prefecture": "大阪",
            "course": "枚方国際ゴルフ倶楽部",
            "tel": "072-858-8311"
        },
        {
            "date": "2月21日",
            "prefecture": "大阪",
            "course": "枚方国際ゴルフ倶楽部",
            "tel": "072-858-8311"
        },
        {
            "date": "2月14日",
            "prefecture": "兵庫",
            "course": "随縁カントリークラブ 西神戸コース",
            "tel": "078-997-9700"
        },
        {
            "date": "2月10日",
            "prefecture": "大阪",
            "course": "枚方国際ゴルフ倶楽部",
            "tel": "072-858-8311"
        },
        {
            "date": "2月8日",
            "prefecture": "兵庫",
            "course": "チェリーゴルフときわ台コース",
            "tel": "072-738-2035"
        },
        {
            "date": "1月30日",
            "prefecture": "大阪",
            "course": "枚方国際ゴルフ倶楽部",
            "tel": "072-858-8311"
        },
        {
            "date": "1月20日",
            "prefecture": "兵庫",
            "course": "チェリーゴルフときわ台コース",
            "tel": "072-738-2035"
        },
        {
            "date": "1月18日",
            "prefecture": "大阪",
            "course": "枚方国際ゴルフ倶楽部",
            "tel": "072-858-8311"
        },
        {
            "date": "1月17日",
            "prefecture": "兵庫",
            "course": "随縁カントリークラブ 西神戸コース",
            "tel": "078-997-9700"
        },
        {
            "date": "1月13日",
            "prefecture": "兵庫",
            "course": "三木セブンハンドレッド倶楽部",
            "tel": "0794-87-3131"
        },
        {
            "date": "1月5日",
            "prefecture": "大阪",
            "course": "枚方国際ゴルフ倶楽部",
            "tel": "072-858-8311"
        },
        {
            "date": "12月30日",
            "prefecture": "大阪",
            "course": "枚方国際ゴルフ倶楽部",
            "tel": "072-858-8311"
        },
        {
            "date": "12月28日",
            "prefecture": "兵庫",
            "course": "チェリーゴルフときわ台コース",
            "tel": "072-738-2035"
        },
        {
            "date": "12月27日",
            "prefecture": "大阪",
            "course": "枚方国際ゴルフ倶楽部",
            "tel": "072-858-8311"
        },
        {
            "date": "12月24日",
            "prefecture": "兵庫",
            "course": "随縁カントリークラブ 西神戸コース",
            "tel": "078-997-9700"
        },
        {
            "date": "12月23日",
            "prefecture": "大阪",
            "course": "枚方国際ゴルフ倶楽部",
            "tel": "072-858-8311"
        },
        {
            "date": "12月21日",
            "prefecture": "兵庫",
            "course": "チェリーゴルフ猪名川コース",
            "tel": "072-769-0301"
        },
        {
            "date": "12月20日",
            "prefecture": "大阪",
            "course": "枚方国際ゴルフ倶楽部",
            "tel": "072-858-8311"
        },
        {
            "date": "12月17日",
            "prefecture": "兵庫",
            "course": "随縁カントリークラブ 西神戸コース",
            "tel": "078-997-9700"
        },
        {
            "date": "12月16日",
            "prefecture": "大阪",
            "course": "枚方国際ゴルフ倶楽部",
            "tel": "072-858-8311"
        },
        {
            "date": "12月14日",
            "prefecture": "兵庫",
            "course": "チェリーゴルフときわ台コース",
            "tel": "072-738-2035"
        },
        {
            "date": "12月13日",
            "prefecture": "大阪",
            "course": "枚方国際ゴルフ倶楽部",
            "tel": "072-858-8311"
        },
        {
            "date": "12月10日",
            "prefecture": "兵庫",
            "course": "随縁カントリークラブ 西神戸コース",
            "tel": "078-997-9700"
        },
        {
            "date": "12月9日",
            "prefecture": "大阪",
            "course": "枚方国際ゴルフ倶楽部",
            "tel": "072-858-8311"
        },
        {
            "date": "12月7日",
            "prefecture": "兵庫",
            "course": "チェリーゴルフ猪名川コース",
            "tel": "072-769-0301"
        },
        {
            "date": "12月6日",
            "prefecture": "大阪",
            "course": "枚方国際ゴルフ倶楽部",
            "tel": "072-858-8311"
        },
        {
            "date": "12月3日",
            "prefecture": "兵庫",
            "course": "随縁カントリークラブ 西神戸コース",
            "tel": "078-997-9700"
        },
        {
            "date": "12月2日",
            "prefecture": "大阪",
            "course": "枚方国際ゴルフ倶楽部",
            "tel": "072-858-8311"
        },
        {
            "date": "11月30日",
            "prefecture": "兵庫",
            "course": "チェリーゴルフときわ台コース",
            "tel": "072-738-2035"
        },
        {
            "date": "11月29日",
            "prefecture": "大阪",
            "course": "枚方国際ゴルフ倶楽部",
            "tel": "072-858-8311"
        },
        {
            "date": "11月26日",
            "prefecture": "兵庫",
            "course": "随縁カントリークラブ 西神戸コース",
            "tel": "078-997-9700"
        },
        {
            "date": "11月25日",
            "prefecture": "大阪",
            "course": "枚方国際ゴルフ倶楽部",
            "tel": "072-858-8311"
        },
        {
            "date": "11月23日",
            "prefecture": "兵庫",
            "course": "チェリーゴルフ猪名川コース",
            "tel": "072-769-0301"
        },
        {
            "date": "11月22日",
            "prefecture": "大阪",
            "course": "枚方国際ゴルフ倶楽部",
            "tel": "072-858-8311"
        },
        {
            "date": "11月19日",
            "prefecture": "兵庫",
            "course": "随縁カントリークラブ 西神戸コース",
            "tel": "078-997-9700"
        },
        {
            "date": "11月18日",
            "prefecture": "大阪",
            "course": "枚方国際ゴルフ倶楽部",
            "tel": "072-858-8311"
        },
        {
            "date": "11月16日",
            "prefecture": "兵庫",
            "course": "チェリーゴルフときわ台コース",
            "tel": "072-738-2035"
        },
        {
            "date": "11月15日",
            "prefecture": "大阪",
            "course": "枚方国際ゴルフ倶楽部",
            "tel": "072-858-8311"
        },
        {
            "date": "11月12日",
            "prefecture": "兵庫",
            "course": "随縁カントリークラブ 西神戸コース",
            "tel": "078-997-9700"
        },
        {
            "date": "11月11日",
            "prefecture": "大阪",
            "course": "枚方国際ゴルフ倶楽部",
            "tel": "072-858-8311"
        },
        {
            "date": "11月9日",
            "prefecture": "兵庫",
            "course": "チェリーゴルフ猪名川コース",
            "tel": "072-769-0301"
        },
        {
            "date": "11月8日",
            "prefecture": "大阪",
            "course": "枚方国際ゴルフ倶楽部",
            "tel": "072-858-8311"
        },
        {
            "date": "11月5日",
            "prefecture": "兵庫",
            "course": "随縁カントリークラブ 西神戸コース",
            "tel": "078-997-9700"
        },
        {
            "date": "11月4日",
            "prefecture": "大阪",
            "course": "枚方国際ゴルフ倶楽部",
            "tel": "072-858-8311"
        },
        {
            "date": "11月2日",
            "prefecture": "兵庫",
            "course": "チェリーゴルフときわ台コース",
            "tel": "072-738-2035"
        },
        {
            "date": "11月1日",
            "prefecture": "大阪",
            "course": "枚方国際ゴルフ倶楽部",
            "tel": "072-858-8311"
        },
        {
            "date": "10月29日",
            "prefecture": "兵庫",
            "course": "随縁カントリークラブ 西神戸コース",
            "tel": "078-997-9700"
        },
        {
            "date": "10月28日",
            "prefecture": "大阪",
            "course": "枚方国際ゴルフ倶楽部",
            "tel": "072-858-8311"
        },
        {
            "date": "10月26日",
            "prefecture": "兵庫",
            "course": "チェリーゴルフ猪名川コース",
            "tel": "072-769-0301"
        },
        {
            "date": "10月25日",
            "prefecture": "大阪",
            "course": "枚方国際ゴルフ倶楽部",
            "tel": "072-858-8311"
        },
        {
            "date": "10月22日",
            "prefecture": "兵庫",
            "course": "随縁カントリークラブ 西神戸コース",
            "tel": "078-997-9700"
        },
        {
            "date": "10月21日",
            "prefecture": "大阪",
            "course": "枚方国際ゴルフ倶楽部",
            "tel": "072-858-8311"
        },
        {
            "date": "10月19日",
            "prefecture": "兵庫",
            "course": "チェリーゴルフときわ台コース",
            "tel": "072-738-2035"
        },
        {
            "date": "10月18日",
            "prefecture": "大阪",
            "course": "枚方国際ゴルフ倶楽部",
            "tel": "072-858-8311"
        },
        {
            "date": "10月15日",
            "prefecture": "兵庫",
            "course": "随縁カントリークラブ 西神戸コース",
            "tel": "078-997-9700"
        },
        {
            "date": "10月14日",
            "prefecture": "大阪",
            "course": "枚方国際ゴルフ倶楽部",
            "tel": "072-858-8311"
        },
        {
            "date": "10月12日",
            "prefecture": "兵庫",
            "course": "チェリーゴルフ猪名川コース",
            "tel": "072-769-0301"
        },
        {
            "date": "10月11日",
            "prefecture": "大阪",
            "course": "枚方国際ゴルフ倶楽部",
            "tel": "072-858-8311"
        },
        {
            "date": "10月8日",
            "prefecture": "兵庫",
            "course": "随縁カントリークラブ 西神戸コース",
            "tel": "078-997-9700"
        },
        {
            "date": "10月7日",
            "prefecture": "大阪",
            "course": "枚方国際ゴルフ倶楽部",
            "tel": "072-858-8311"
        },
        {
            "date": "10月5日",
            "prefecture": "兵庫",
            "course": "チェリーゴルフときわ台コース",
            "tel": "072-738-2035"
        },
        {
            "date": "10月4日",
            "prefecture": "大阪",
            "course": "枚方国際ゴルフ倶楽部",
            "tel": "072-858-8311"
        },
        {
            "date": "10月1日",
            "prefecture": "兵庫",
            "course": "随縁カントリークラブ 西神戸コース",
            "tel": "078-997-9700"
        },
        {
            "date": "9月30日",
            "prefecture": "大阪",
            "course": "枚方国際ゴルフ倶楽部",
            "tel": "072-858-8311"
        },
        {
            "date": "9月28日",
            "prefecture": "兵庫",
            "course": "チェリーゴルフ猪名川コース",
            "tel": "072-769-0301"
        },
        {
            "date": "9月27日",
            "prefecture": "大阪",
            "course": "枚方国際ゴルフ倶楽部",
            "tel": "072-858-8311"
        },
        {
            "date": "9月24日",
            "prefecture": "兵庫",
            "course": "随縁カントリークラブ 西神戸コース",
            "tel": "078-997-9700"
        },
        {
            "date": "9月23日",
            "prefecture": "大阪",
            "course": "枚方国際ゴルフ倶楽部",
            "tel": "072-858-8311"
        },
        {
            "date": "9月21日",
            "prefecture": "兵庫",
            "course": "チェリーゴルフときわ台コース",
            "tel": "072-738-2035"
        },
        {
            "date": "9月20日",
            "prefecture": "大阪",
            "course": "枚方国際ゴルフ倶楽部",
            "tel": "072-858-8311"
        },
        {
            "date": "9月17日",
            "prefecture": "兵庫",
            "course": "随縁カントリークラブ 西神戸コース",
            "tel": "078-997-9700"
        },
        {
            "date": "9月16日",
            "prefecture": "大阪",
            "course": "枚方国際ゴルフ倶楽部",
            "tel": "072-858-8311"
        },
        {
            "date": "9月14日",
            "prefecture": "兵庫",
            "course": "チェリーゴルフ猪名川コース",
            "tel": "072-769-0301"
        },
        {
            "date": "9月13日",
            "prefecture": "大阪",
            "course": "枚方国際ゴルフ倶楽部",
            "tel": "072-858-8311"
        },
        {
            "date": "9月10日",
            "prefecture": "兵庫",
            "course": "随縁カントリークラブ 西神戸コース",
            "tel": "078-997-9700"
        },
        {
            "date": "9月9日",
            "prefecture": "大阪",
            "course": "枚方国際ゴルフ倶楽部",
            "tel": "072-858-8311"
        },
        {
            "date": "9月7日",
            "prefecture": "兵庫",
            "course": "チェリーゴルフときわ台コース",
            "tel": "072-738-2035"
        },
        {
            "date": "9月6日",
            "prefecture": "大阪",
            "course": "枚方国際ゴルフ倶楽部",
            "tel": "072-858-8311"
        },
        {
            "date": "9月3日",
            "prefecture": "兵庫",
            "course": "随縁カントリークラブ 西神戸コース",
            "tel": "078-997-9700"
        },
        {
            "date": "9月2日",
            "prefecture": "大阪",
            "course": "枚方国際ゴルフ倶楽部",
            "tel": "072-858-8311"
        },
        {
            "date": "8月31日",
            "prefecture": "兵庫",
            "course": "チェリーゴルフ猪名川コース",
            "tel": "072-769-0301"
        },
        {
            "date": "8月30日",
            "prefecture": "大阪",
            "course": "枚方国際ゴルフ倶楽部",
            "tel": "072-858-8311"
        },
        {
            "date": "8月27日",
            "prefecture": "兵庫",
            "course": "随縁カントリークラブ 西神戸コース",
            "tel": "078-997-9700"
        },
        {
            "date": "8月26日",
            "prefecture": "大阪",
            "course": "枚方国際ゴルフ倶楽部",
            "tel": "072-858-8311"
        },
        {
            "date": "8月24日",
            "prefecture": "兵庫",
            "course": "チェリーゴルフときわ台コース",
            "tel": "072-738-2035"
        },
        {
            "date": "8月23日",
            "prefecture": "大阪",
            "course": "枚方国際ゴルフ倶楽部",
            "tel": "072-858-8311"
        },
        {
            "date": "8月20日",
            "prefecture": "兵庫",
            "course": "随縁カントリークラブ 西神戸コース",
            "tel": "078-997-9700"
        },
        {
            "date": "8月19日",
            "prefecture": "大阪",
            "course": "枚方国際ゴルフ倶楽部",
            "tel": "072-858-8311"
        },
        {
            "date": "8月17日",
            "prefecture": "兵庫",
            "course": "チェリーゴルフ猪名川コース",
            "tel": "072-769-0301"
        },
        {
            "date": "8月16日",
            "prefecture": "大阪",
            "course": "枚方国際ゴルフ倶楽部",
            "tel": "072-858-8311"
        },
        {
            "date": "8月13日",
            "prefecture": "兵庫",
            "course": "随縁カントリークラブ 西神戸コース",
            "tel": "078-997-9700"
        },
        {
            "date": "8月12日",
            "prefecture": "大阪",
            "course": "枚方国際ゴルフ倶楽部",
            "tel": "072-858-8311"
        },
        {
            "date": "8月10日",
            "prefecture": "兵庫",
            "course": "チェリーゴルフときわ台コース",
            "tel": "072-738-2035"
        },
        {
            "date": "8月9日",
            "prefecture": "大阪",
            "course": "枚方国際ゴルフ倶楽部",
            "tel": "072-858-8311"
        },
        {
            "date": "8月6日",
            "prefecture": "兵庫",
            "course": "随縁カントリークラブ 西神戸コース",
            "tel": "078-997-9700"
        },
        {
            "date": "8月5日",
            "prefecture": "大阪",
            "course": "枚方国際ゴルフ倶楽部",
            "tel": "072-858-8311"
        },
        {
            "date": "8月3日",
            "prefecture": "兵庫",
            "course": "チェリーゴルフ猪名川コース",
            "tel": "072-769-0301"
        },
        {
            "date": "8月2日",
            "prefecture": "大阪",
            "course": "枚方国際ゴルフ倶楽部",
            "tel": "072-858-8311"
        },
        {
            "date": "7月30日",
            "prefecture": "兵庫",
            "course": "随縁カントリークラブ 西神戸コース",
            "tel": "078-997-9700"
        },
        {
            "date": "7月29日",
            "prefecture": "大阪",
            "course": "枚方国際ゴルフ倶楽部",
            "tel": "072-858-8311"
        },
        {
            "date": "7月27日",
            "prefecture": "兵庫",
            "course": "チェリーゴルフときわ台コース",
            "tel": "072-738-2035"
        },
        {
            "date": "7月26日",
            "prefecture": "大阪",
            "course": "枚方国際ゴルフ倶楽部",
            "tel": "072-858-8311"
        },
        {
            "date": "7月23日",
            "prefecture": "兵庫",
            "course": "随縁カントリークラブ 西神戸コース",
            "tel": "078-997-9700"
        },
        {
            "date": "7月22日",
            "prefecture": "大阪",
            "course": "枚方国際ゴルフ倶楽部",
            "tel": "072-858-8311"
        },
        {
            "date": "7月20日",
            "prefecture": "兵庫",
            "course": "チェリーゴルフ猪名川コース",
            "tel": "072-769-0301"
        },
        {
            "date": "7月19日",
            "prefecture": "大阪",
            "course": "枚方国際ゴルフ倶楽部",
            "tel": "072-858-8311"
        },
        {
            "date": "7月16日",
            "prefecture": "兵庫",
            "course": "随縁カントリークラブ 西神戸コース",
            "tel": "078-997-9700"
        },
        {
            "date": "7月15日",
            "prefecture": "大阪",
            "course": "枚方国際ゴルフ倶楽部",
            "tel": "072-858-8311"
        },
        {
            "date": "7月13日",
            "prefecture": "兵庫",
            "course": "チェリーゴルフときわ台コース",
            "tel": "072-738-2035"
        },
        {
            "date": "7月12日",
            "prefecture": "大阪",
            "course": "枚方国際ゴルフ倶楽部",
            "tel": "072-858-8311"
        },
        {
            "date": "7月9日",
            "prefecture": "兵庫",
            "course": "随縁カントリークラブ 西神戸コース",
            "tel": "078-997-9700"
        },
        {
            "date": "7月8日",
            "prefecture": "大阪",
            "course": "枚方国際ゴルフ倶楽部",
            "tel": "072-858-8311"
        },
        {
            "date": "7月6日",
            "prefecture": "兵庫",
            "course": "チェリーゴルフ猪名川コース",
            "tel": "072-769-0301"
        },
        {
            "date": "7月5日",
            "prefecture": "大阪",
            "course": "枚方国際ゴルフ倶楽部",
            "tel": "072-858-8311"
        },
        {
            "date": "7月2日",
            "prefecture": "兵庫",
            "course": "随縁カントリークラブ 西神戸コース",
            "tel": "078-997-9700"
        },
        {
            "date": "7月1日",
            "prefecture": "大阪",
            "course": "枚方国際ゴルフ倶楽部",
            "tel": "072-858-8311"
        },
        {
            "date": "6月29日",
            "prefecture": "兵庫",
            "course": "チェリーゴルフときわ台コース",
            "tel": "072-738-2035"
        },
        {
            "date": "6月28日",
            "prefecture": "大阪",
            "course": "枚方国際ゴルフ倶楽部",
            "tel": "072-858-8311"
        },
        {
            "date": "6月25日",
            "prefecture": "兵庫",
            "course": "随縁カントリークラブ 西神戸コース",
            "tel": "078-997-9700"
        },
        {
            "date": "6月24日",
            "prefecture": "大阪",
            "course": "枚方国際ゴルフ倶楽部",
            "tel": "072-858-8311"
        },
        {
            "date": "6月22日",
            "prefecture": "兵庫",
            "course": "チェリーゴルフ猪名川コース",
            "tel": "072-769-0301"
        },
        {
            "date": "6月21日",
            "prefecture": "大阪",
            "course": "枚方国際ゴルフ倶楽部",
            "tel": "072-858-8311"
        },
        {
            "date": "6月18日",
            "prefecture": "兵庫",
            "course": "随縁カントリークラブ 西神戸コース",
            "tel": "078-997-9700"
        },
        {
            "date": "6月17日",
            "prefecture": "大阪",
            "course": "枚方国際ゴルフ倶楽部",
            "tel": "072-858-8311"
        },
        {
            "date": "6月15日",
            "prefecture": "兵庫",
            "course": "チェリーゴルフときわ台コース",
            "tel": "072-738-2035"
        },
        {
            "date": "6月14日",
            "prefecture": "大阪",
            "course": "枚方国際ゴルフ倶楽部",
            "tel": "072-858-8311"
        },
        {
            "date": "6月11日",
            "prefecture": "兵庫",
            "course": "随縁カントリークラブ 西神戸コース",
            "tel": "078-997-9700"
        },
        {
            "date": "6月10日",
            "prefecture": "大阪",
            "course": "枚方国際ゴルフ倶楽部",
            "tel": "072-858-8311"
        },
        {
            "date": "6月8日",
            "prefecture": "兵庫",
            "course": "チェリーゴルフ猪名川コース",
            "tel": "072-769-0301"
        },
        {
            "date": "6月7日",
            "prefecture": "大阪",
            "course": "枚方国際ゴルフ倶楽部",
            "tel": "072-858-8311"
        },
        {
            "date": "6月4日",
            "prefecture": "兵庫",
            "course": "随縁カントリークラブ 西神戸コース",
            "tel": "078-997-9700"
        },
        {
            "date": "6月3日",
            "prefecture": "大阪",
            "course": "枚方国際ゴルフ倶楽部",
            "tel": "072-858-8311"
        },
        {
            "date": "6月1日",
            "prefecture": "兵庫",
            "course": "チェリーゴルフときわ台コース",
            "tel": "072-738-2035"
        },
        {
            "date": "5月31日",
            "prefecture": "大阪",
            "course": "枚方国際ゴルフ倶楽部",
            "tel": "072-858-8311"
        },
        {
            "date": "5月28日",
            "prefecture": "兵庫",
            "course": "随縁カントリークラブ 西神戸コース",
            "tel": "078-997-9700"
        },
        {
            "date": "5月27日",
            "prefecture": "大阪",
            "course": "枚方国際ゴルフ倶楽部",
            "tel": "072-858-8311"
        },
        {
            "date": "5月25日",
            "prefecture": "兵庫",
            "course": "チェリーゴルフ猪名川コース",
            "tel": "072-769-0301"
        },
        {
            "date": "5月24日",
            "prefecture": "大阪",
            "course": "枚方国際ゴルフ倶楽部",
            "tel": "072-858-8311"
        },
        {
            "date": "5月21日",
            "prefecture": "兵庫",
            "course": "随縁カントリークラブ 西神戸コース",
            "tel": "078-997-9700"
        },
        {
            "date": "5月20日",
            "prefecture": "大阪",
            "course": "枚方国際ゴルフ倶楽部",
            "tel": "072-858-8311"
        },
        {
            "date": "5月18日",
            "prefecture": "兵庫",
            "course": "チェリーゴルフときわ台コース",
            "tel": "072-738-2035"
        },
        {
            "date": "5月17日",
            "prefecture": "大阪",
            "course": "枚方国際ゴルフ倶楽部",
            "tel": "072-858-8311"
        },
        {
            "date": "5月14日",
            "prefecture": "兵庫",
            "course": "随縁カントリークラブ 西神戸コース",
            "tel": "078-997-9700"
        },
        {
            "date": "5月13日",
            "prefecture": "大阪",
            "course": "枚方国際ゴルフ倶楽部",
            "tel": "072-858-8311"
        },
        {
            "date": "5月11日",
            "prefecture": "兵庫",
            "course": "チェリーゴルフ猪名川コース",
            "tel": "072-769-0301"
        },
        {
            "date": "5月10日",
            "prefecture": "大阪",
            "course": "枚方国際ゴルフ倶楽部",
            "tel": "072-858-8311"
        },
        {
            "date": "5月7日",
            "prefecture": "兵庫",
            "course": "随縁カントリークラブ 西神戸コース",
            "tel": "078-997-9700"
        },
        {
            "date": "5月6日",
            "prefecture": "大阪",
            "course": "枚方国際ゴルフ倶楽部",
            "tel": "072-858-8311"
        },
        {
            "date": "5月4日",
            "prefecture": "兵庫",
            "course": "チェリーゴルフときわ台コース",
            "tel": "072-738-2035"
        },
        {
            "date": "5月3日",
            "prefecture": "大阪",
            "course": "枚方国際ゴルフ倶楽部",
            "tel": "072-858-8311"
        },
        {
            "date": "4月30日",
            "prefecture": "兵庫",
            "course": "随縁カントリークラブ 西神戸コース",
            "tel": "078-997-9700"
        },
        {
            "date": "4月29日",
            "prefecture": "大阪",
            "course": "枚方国際ゴルフ倶楽部",
            "tel": "072-858-8311"
        },
        {
            "date": "4月27日",
            "prefecture": "兵庫",
            "course": "チェリーゴルフ猪名川コース",
            "tel": "072-769-0301"
        },
        {
            "date": "4月26日",
            "prefecture": "大阪",
            "course": "枚方国際ゴルフ倶楽部",
            "tel": "072-858-8311"
        },
        {
            "date": "4月23日",
            "prefecture": "兵庫",
            "course": "随縁カントリークラブ 西神戸コース",
            "tel": "078-997-9700"
        },
        {
            "date": "4月22日",
            "prefecture": "大阪",
            "course": "枚方国際ゴルフ倶楽部",
            "tel": "072-858-8311"
        },
        {
            "date": "4月20日",
            "prefecture": "兵庫",
            "course": "チェリーゴルフときわ台コース",
            "tel": "072-738-2035"
        },
        {
            "date": "4月19日",
            "prefecture": "大阪",
            "course": "枚方国際ゴルフ倶楽部",
            "tel": "072-858-8311"
        },
        {
            "date": "4月16日",
            "prefecture": "兵庫",
            "course": "随縁カントリークラブ 西神戸コース",
            "tel": "078-997-9700"
        },
        {
            "date": "4月15日",
            "prefecture": "大阪",
            "course": "枚方国際ゴルフ倶楽部",
            "tel": "072-858-8311"
        },
        {
            "date": "4月13日",
            "prefecture": "兵庫",
            "course": "チェリーゴルフ猪名川コース",
            "tel": "072-769-0301"
        },
        {
            "date": "4月12日",
            "prefecture": "大阪",
            "course": "枚方国際ゴルフ倶楽部",
            "tel": "072-858-8311"
        },
        {
            "date": "4月9日",
            "prefecture": "兵庫",
            "course": "随縁カントリークラブ 西神戸コース",
            "tel": "078-997-9700"
        },
        {
            "date": "4月8日",
            "prefecture": "大阪",
            "course": "枚方国際ゴルフ倶楽部",
            "tel": "072-858-8311"
        },
        {
            "date": "4月6日",
            "prefecture": "兵庫",
            "course": "チェリーゴルフときわ台コース",
            "tel": "072-738-2035"
        },
        {
            "date": "4月5日",
            "prefecture": "大阪",
            "course": "枚方国際ゴルフ倶楽部",
            "tel": "072-858-8311"
        },
        {
            "date": "4月2日",
            "prefecture": "兵庫",
            "course": "随縁カントリークラブ 西神戸コース",
            "tel": "078-997-9700"
        },
        {
            "date": "4月1日",
            "prefecture": "大阪",
            "course": "枚方国際ゴルフ倶楽部",
            "tel": "072-858-8311"
        },
        {
            "date": "3月31日",
            "prefecture": "兵庫",
            "course": "チェリーゴルフ猪名川コース",
            "tel": "072-769-0301"
        },
        {
            "date": "3月30日",
            "prefecture": "大阪",
            "course": "枚方国際ゴルフ倶楽部",
            "tel": "072-858-8311"
        },
        {
            "date": "3月27日",
            "prefecture": "兵庫",
            "course": "随縁カントリークラブ 西神戸コース",
            "tel": "078-997-9700"
        },
        {
            "date": "3月26日",
            "prefecture": "大阪",
            "course": "枚方国際ゴルフ倶楽部",
            "tel": "072-858-8311"
        },
        {
            "date": "3月24日",
            "prefecture": "兵庫",
            "course": "チェリーゴルフときわ台コース",
            "tel": "072-738-2035"
        },
        {
            "date": "3月23日",
            "prefecture": "大阪",
            "course": "枚方国際ゴルフ倶楽部",
            "tel": "072-858-8311"
        },
        {
            "date": "3月20日",
            "prefecture": "兵庫",
            "course": "随縁カントリークラブ 西神戸コース",
            "tel": "078-997-9700"
        },
        {
            "date": "3月19日",
            "prefecture": "大阪",
            "course": "枚方国際ゴルフ倶楽部",
            "tel": "072-858-8311"
        },
        {
            "date": "3月17日",
            "prefecture": "兵庫",
            "course": "チェリーゴルフ猪名川コース",
            "tel": "072-769-0301"
        },
        {
            "date": "3月16日",
            "prefecture": "大阪",
            "course": "枚方国際ゴルフ倶楽部",
            "tel": "072-858-8311"
        },
        {
            "date": "3月13日",
            "prefecture": "兵庫",
            "course": "随縁カントリークラブ 西神戸コース",
            "tel": "078-997-9700"
        },
        {
            "date": "3月12日",
            "prefecture": "大阪",
            "course": "枚方国際ゴルフ倶楽部",
            "tel": "072-858-8311"
        },
        {
            "date": "3月10日",
            "prefecture": "兵庫",
            "course": "チェリーゴルフときわ台コース",
            "tel": "072-738-2035"
        },
        {
            "date": "3月9日",
            "prefecture": "大阪",
            "course": "枚方国際ゴルフ倶楽部",
            "tel": "072-858-8311"
        },
        {
            "date": "3月6日",
            "prefecture": "兵庫",
            "course": "随縁カントリークラブ 西神戸コース",
            "tel": "078-997-9700"
        },
        {
            "date": "3月5日",
            "prefecture": "大阪",
            "course": "枚方国際ゴルフ倶楽部",
            "tel": "072-858-8311"
        },
        {
            "date": "3月3日",
            "prefecture": "兵庫",
            "course": "チェリーゴルフ猪名川コース",
            "tel": "072-769-0301"
        },
        {
            "date": "3月2日",
            "prefecture": "大阪",
            "course": "枚方国際ゴルフ倶楽部",
            "tel": "072-858-8311"
        },
        {
            "date": "2月27日",
            "prefecture": "兵庫",
            "course": "随縁カントリークラブ 西神戸コース",
            "tel": "078-997-9700"
        },
        {
            "date": "2月26日",
            "prefecture": "大阪",
            "course": "枚方国際ゴルフ倶楽部",
            "tel": "072-858-8311"
        },
        {
            "date": "2月24日",
            "prefecture": "兵庫",
            "course": "チェリーゴルフときわ台コース",
            "tel": "072-738-2035"
        },
        {
            "date": "2月23日",
            "prefecture": "大阪",
            "course": "枚方国際ゴルフ倶楽部",
            "tel": "072-858-8311"
        },
        {
            "date": "2月20日",
            "prefecture": "兵庫",
            "course": "随縁カントリークラブ 西神戸コース",
            "tel": "078-997-9700"
        },
        {
            "date": "2月19日",
            "prefecture": "大阪",
            "course": "枚方国際ゴルフ倶楽部",
            "tel": "072-858-8311"
        },
        {
            "date": "2月17日",
            "prefecture": "兵庫",
            "course": "チェリーゴルフ猪名川コース",
            "tel": "072-769-0301"
        },
        {
            "date": "2月16日",
            "prefecture": "大阪",
            "course": "枚方国際ゴルフ倶楽部",
            "tel": "072-858-8311"
        },
        {
            "date": "2月13日",
            "prefecture": "兵庫",
            "course": "随縁カントリークラブ 西神戸コース",
            "tel": "078-997-9700"
        },
        {
            "date": "2月12日",
            "prefecture": "大阪",
            "course": "枚方国際ゴルフ倶楽部",
            "tel": "072-858-8311"
        },
        {
            "date": "2月10日",
            "prefecture": "兵庫",
            "course": "チェリーゴルフときわ台コース",
            "tel": "072-738-2035"
        },
        {
            "date": "2月9日",
            "prefecture": "大阪",
            "course": "枚方国際ゴルフ倶楽部",
            "tel": "072-858-8311"
        },
        {
            "date": "2月6日",
            "prefecture": "兵庫",
            "course": "随縁カントリークラブ 西神戸コース",
            "tel": "078-997-9700"
        },
        {
            "date": "2月5日",
            "prefecture": "大阪",
            "course": "枚方国際ゴルフ倶楽部",
            "tel": "072-858-8311"
        },
        {
            "date": "2月3日",
            "prefecture": "兵庫",
            "course": "チェリーゴルフ猪名川コース",
            "tel": "072-769-0301"
        },
        {
            "date": "2月2日",
            "prefecture": "大阪",
            "course": "枚方国際ゴルフ倶楽部",
            "tel": "072-858-8311"
        },
        {
            "date": "1月30日",
            "prefecture": "兵庫",
            "course": "随縁カントリークラブ 西神戸コース",
            "tel": "078-997-9700"
        },
        {
            "date": "1月29日",
            "prefecture": "大阪",
            "course": "枚方国際ゴルフ倶楽部",
            "tel": "072-858-8311"
        },
        {
            "date": "1月27日",
            "prefecture": "兵庫",
            "course": "チェリーゴルフときわ台コース",
            "tel": "072-738-2035"
        },
        {
            "date": "1月26日",
            "prefecture": "大阪",
            "course": "枚方国際ゴルフ倶楽部",
            "tel": "072-858-8311"
        },
        {
            "date": "1月23日",
            "prefecture": "兵庫",
            "course": "随縁カントリークラブ 西神戸コース",
            "tel": "078-997-9700"
        },
        {
            "date": "1月22日",
            "prefecture": "大阪",
            "course": "枚方国際ゴルフ倶楽部",
            "tel": "072-858-8311"
        },
        {
            "date": "1月20日",
            "prefecture": "兵庫",
            "course": "チェリーゴルフ猪名川コース",
            "tel": "072-769-0301"
        },
        {
            "date": "1月19日",
            "prefecture": "大阪",
            "course": "枚方国際ゴルフ倶楽部",
            "tel": "072-858-8311"
        },
        {
            "date": "1月16日",
            "prefecture": "兵庫",
            "course": "随縁カントリークラブ 西神戸コース",
            "tel": "078-997-9700"
        },
        {
            "date": "1月15日",
            "prefecture": "大阪",
            "course": "枚方国際ゴルフ倶楽部",
            "tel": "072-858-8311"
        },
        {
            "date": "1月13日",
            "prefecture": "兵庫",
            "course": "チェリーゴルフときわ台コース",
            "tel": "072-738-2035"
        },
        {
            "date": "1月12日",
            "prefecture": "大阪",
            "course": "枚方国際ゴルフ倶楽部",
            "tel": "072-858-8311"
        },
        {
            "date": "1月9日",
            "prefecture": "兵庫",
            "course": "随縁カントリークラブ 西神戸コース",
            "tel": "078-997-9700"
        },
        {
            "date": "1月8日",
            "prefecture": "大阪",
            "course": "枚方国際ゴルフ倶楽部",
            "tel": "072-858-8311"
        },
        {
            "date": "1月6日",
            "prefecture": "兵庫",
            "course": "チェリーゴルフ猪名川コース",
            "tel": "072-769-0301"
        },
        {
            "date": "1月5日",
            "prefecture": "大阪",
            "course": "枚方国際ゴルフ倶楽部",
            "tel": "072-858-8311"
        }
    ]
} 